qamlib.cpython-310-x86_64-linux-gnu.so
qamlib-0.11.0.dist-info/LICENSE.LGPL2.1
qamlib-0.11.0.dist-info/METADATA
qamlib-0.11.0.dist-info/WHEEL
qamlib-0.11.0.dist-info/RECORD
