Metadata-Version: 2.1
Name: qamlib
Version: 0.11.0
Summary: A library for interacting with Video4Linux2 (V4L2) video devices
Author-Email: Daniel Lundberg Pedersen <dlp@qtec.com>
License:                   GNU LESSER GENERAL PUBLIC LICENSE
Classifier: Programming Language :: C++
Classifier: Operating System :: POSIX :: Linux
Classifier: Topic :: Multimedia :: Video
Classifier: Topic :: Multimedia :: Video :: Capture
Project-URL: Homepage, https://gitlab.com/qtec/public/qamlib
Project-URL: Documentation, https://qtec.gitlab.io/public/qamlib/index.html
Project-URL: Changelog, https://qtec.gitlab.io/public/qamlib/changelog.html
Project-URL: Source, https://gitlab.com/qtec/public/qamlib
Project-URL: Issues, https://gitlab.com/qtec/public/qamlib/issues
Requires-Python: >=3.8
Requires-Dist: numpy
